{
    "PATIENT_ID": 2598,
    "AGE": 47,
    "SEX": "M",
    "PATHOLOGY": "boerhaave",
    "Symptomatology": "Do you feel pain somewhere?: hypochondrium(R)\nDo you have pain somewhere, related to your reason for consulting?: TRUE\nDoes the pain radiate to another location?: scapula(R)\nCharacterize your pain:: violent\nHow fast did the pain appear?: 8\nHow intense is the pain?: 8\nHow precisely is the pain located?: 5",
    "Lifestyle": "Do you drink alcohol excessively or do you have an addiction to alcohol?: TRUE",
    "Exposure": "Have you traveled out of the country in the last 4 weeks?: N"
}